termadaptor/__init__.py
termadaptor/__main__.py
termadaptor/cli.py
termadaptor/lib.py
termadaptor-0.0.2.dist-info/LICENSE
termadaptor-0.0.2.dist-info/METADATA
termadaptor-0.0.2.dist-info/WHEEL
termadaptor-0.0.2.dist-info/entry_points.txt
termadaptor-0.0.2.dist-info/top_level.txt
termadaptor-0.0.2.dist-info/RECORD
