Metadata-Version: 2.1
Name: termadaptor
Version: 0.0.2
Summary: A real terminal adaptor for AI agents
Home-page: https://github.com/james4ever0/agent-terminal-adaptor
License: This is free and unencumbered software released into the public domain.
License-File: LICENSE
Requires-Dist: parse
Requires-Dist: playwright
Requires-Dist: beautifulsoup4
